pyanime/TypeAnime.py
pyanime/__init__.py
pyanime/main.py
pyanime/servers.py
pyanime/watch.py
pyanime/search/__init__.py
pyanime/search/anime.py
pyanime-1.1.1.dist-info/LICENSE
pyanime-1.1.1.dist-info/METADATA
pyanime-1.1.1.dist-info/WHEEL
pyanime-1.1.1.dist-info/top_level.txt
pyanime-1.1.1.dist-info/RECORD
